TTNe/__init__.py
TTNe/analytic.py
TTNe/analytic_multi.py
TTNe/inference_utility.py
TTNe/plot.py
TTNe/run.py
TTNe/simulation/ts_utility.py
TTNe/simulation/ts_utility_wholeGenome.py
TTNe/simulation/tweakIBD.py
TTNe/simulation/tweakIBD_helper.py
TTNe-0.0.1a0.dist-info/LICENSE
TTNe-0.0.1a0.dist-info/METADATA
TTNe-0.0.1a0.dist-info/WHEEL
TTNe-0.0.1a0.dist-info/entry_points.txt
TTNe-0.0.1a0.dist-info/top_level.txt
TTNe-0.0.1a0.dist-info/RECORD
